{
  "OilRig": {      
    "name": "OilRig",
    "file": "OilRig.png",
    "offsetNav": [173,162],
    "offsetTrade": [345,325],
    "offsetInfo": [345,325],
    
    "produces": ["Petroleum"],
    "accepts": []
  },
  "Forest": {
    "name": "Forest",
    "file": "Forest.png",
    "offsetNav": [193,165],
    "offsetTrade": [345,325],
    "offsetInfo": [345,325],

    "produces": ["Wood"],
    "accepts": []
  },
  "IronMine": {
    "name": "Iron mine",
    "file": "Iron.png",
    "offsetNav": [173,162],
    "offsetTrade": [345,325],
    "offsetInfo": [345,325],

    "produces": ["Iron"],
    "accepts": []
  },
  "CopperMine": {
    "name": "Copper mine",
    "file": "Copper.png",
    "offsetNav": [200,275],
    "offsetTrade": [400,550],
    "offsetInfo": [345,325],

    "produces": ["Copper"],
    "accepts": []
  },
  "Container": {
    "name": "Container workshop",
    "file": "Container.png",
    "offsetNav": [200,275],
    "offsetTrade": [400,550],
    "offsetInfo": [345,325],

    "produces": ["Container"],
    "accepts": []
  },
  "ClayMine": {
    "name": "ClayMine",
    "file": "ClayMine.png",        
    "offsetNav": [200,275],
    "offsetTrade": [387,439],
    "offsetInfo": [345,325],
    
    "produces": ["Clay"],
    "accepts": []
  },
  "BrickFactory": {
    "name": "Brick Factory",
    "file": "BrickFactory.png",
    "offsetNav": [200,275],
    "offsetTrade": [388,358],
    "offsetInfo": [345,325],

    "produces": ["Bricks"],
    "accepts": ["Clay"]
  },
  "Farm": {
    "name": "Farm",
    "file": "Farm.png",        
    "offsetNav": [193,186],
    "offsetTrade": [385,372],
    "offsetInfo": [345,325],

    "produces": ["Livestock"],
    "accepts": ["Water"]
  },
  "Powerplant": {
    "name": "PowerPlant",
    "file": "Powerplant.png",
    "offsetNav": [200,275],
    "offsetTrade": [400,550],
    "offsetInfo": [345,325],
    
    "produces": [],
    "accepts": ["Coal"]
  },
  "OilProcessing": {
    "name": "Oil industry",
    "file": "OilProcessing.png",
    "offsetNav": [193,271],
    "offsetTrade": [385,543],
    "offsetInfo": [345,325],

    "produces": ["Oil", "Gasoline"],
    "accepts": ["Petroleum"]
  },
  "Grain": {
    "name": "Grain",
    "file": "Grain.png",    
    "offsetNav": [200,275],
    "offsetTrade": [400,550],
    "offsetInfo": [345,325],
    
    "produces": ["Grain"],
    "accepts": ["Water"]
  },
  "Chemical": {
    "name": "Chemical",
    "file": "Chemical.png",
    "offsetNav": [193,245],
    "offsetTrade": [385,490],
    "offsetInfo": [345,325],

    "produces": ["Oil", "Gasoline"],
    "accepts": ["Petroleum"]
  },
  "Lumber": {
    "name": "Lumber",
    "file": "LumberMill.png",        
    "offsetNav": [195,275],
    "offsetTrade": [400,550],
    "offsetInfo": [345,325],

    "produces": ["WoodPlank"],
    "accepts": ["Wood"]
  }
}